tarvis/tradingbot/__init__.py
tarvis_tradingbot-0.9.9.dist-info/LICENSE.txt
tarvis_tradingbot-0.9.9.dist-info/METADATA
tarvis_tradingbot-0.9.9.dist-info/WHEEL
tarvis_tradingbot-0.9.9.dist-info/entry_points.txt
tarvis_tradingbot-0.9.9.dist-info/top_level.txt
tarvis_tradingbot-0.9.9.dist-info/RECORD
