Metadata-Version: 2.1
Name: tarvis-tradingbot
Version: 0.9.9
Summary: Tarvis Trading Bot
Home-page: https://tarvislabs.com/
Author: Tarvis Labs
Author-email: python@tarvislabs.com
License: MIT
Platform: UNKNOWN
Classifier: License :: OSI Approved :: MIT License
Requires-Python: >=3.10
License-File: LICENSE.txt
Requires-Dist: tarvis-atb (==0.9.9)
Requires-Dist: tarvis-exchange-binance (==0.9.9)
Requires-Dist: tarvis-exchange-dydx (==0.9.9)
Requires-Dist: tarvis-exchange-woo (==0.9.9)
Requires-Dist: tarvis-indicators-webapi (==0.9.9)
